{
  "version": "7",
  "dialect": "postgresql",
  "entries": [
    {
      "idx": 0,
      "version": "7",
      "when": 1778145790682,
      "tag": "0000_illegal_bloodstorm",
      "breakpoints": true
    },
    {
      "idx": 1,
      "version": "7",
      "when": 1778239764776,
      "tag": "0001_panoramic_madame_web",
      "breakpoints": true
    },
    {
      "idx": 2,
      "version": "7",
      "when": 1779228031219,
      "tag": "0003_lying_alex_power",
      "breakpoints": true
    },
    {
      "idx": 3,
      "version": "7",
      "when": 1779395364803,
      "tag": "0003_shocking_wallop",
      "breakpoints": true
    },
    {
      "idx": 4,
      "version": "7",
      "when": 1779724044010,
      "tag": "0004_mute_ravenous",
      "breakpoints": true
    }
  ]
}